secmail/__init__.py
secmail/client.py
secmail/config.py
secmail/models.py
1secMail-1.2.0.dist-info/LICENSE
1secMail-1.2.0.dist-info/METADATA
1secMail-1.2.0.dist-info/WHEEL
1secMail-1.2.0.dist-info/top_level.txt
1secMail-1.2.0.dist-info/RECORD
