Metadata-Version: 2.1
Name: 1secMail
Version: 1.2.0
Summary: 📧 Simple and intuitive, yet full featured API wrapper for www.1secmail.com, supporting both synchronous and asynchronous operations.
Home-page: https://github.com/qvco/1secMail-Python
Download-URL: https://github.com/qvco/1secMail-Python
Author: qvco
Author-email: nikola.desuga@gmail.com
Maintainer: qvco
Maintainer-email: nikola.desuga@gmail.com
License: MIT
Keywords: 1secmail,onesecmail,tempmail,disposable,temporary,email,api,wrapper,library,async,asynchronous
Classifier: License :: OSI Approved :: MIT License
Classifier: Programming Language :: Python :: 3
Classifier: Programming Language :: Python :: 3.8
Classifier: Programming Language :: Python :: 3.9
Classifier: Programming Language :: Python :: 3.10
Classifier: Programming Language :: Python :: 3.11
License-File: LICENSE
Requires-Dist: httpx (>=0.17.1)
